.flake8
.travis.yml
LICENSE
MANIFEST.in
Makefile
README.rst
requirements-dev.txt
requirements.txt
setup.py
slicedimage/__init__.py
slicedimage/_augmentedenum.py
slicedimage/_collection.py
slicedimage/_compat.py
slicedimage/_dimensions.py
slicedimage/_formats.py
slicedimage/_tile.py
slicedimage/_tileset.py
slicedimage/_typeformatting.py
slicedimage/urlpath.py
slicedimage.egg-info/PKG-INFO
slicedimage.egg-info/SOURCES.txt
slicedimage.egg-info/dependency_links.txt
slicedimage.egg-info/entry_points.txt
slicedimage.egg-info/requires.txt
slicedimage.egg-info/top_level.txt
slicedimage/backends/__init__.py
slicedimage/backends/_base.py
slicedimage/backends/_caching.py
slicedimage/backends/_disk.py
slicedimage/backends/_http.py
slicedimage/backends/_s3.py
slicedimage/cli/__init__.py
slicedimage/cli/__main__.py
slicedimage/cli/_base.py
slicedimage/cli/checksum.py
slicedimage/cli/main.py
slicedimage/io/__init__.py
slicedimage/io/_base.py
slicedimage/io/_keys.py
slicedimage/io/_v0_0_0.py
slicedimage/io/_v0_1_0.py
slicedimage/url/__init__.py
slicedimage/url/path.py
slicedimage/url/resolve.py
slicedimage/url/test/__init__.py
slicedimage/url/test/test_calculate_relative_url.py
tests/__init__.py
tests/test_tile_coordinates.py
tests/io_/__init__.py
tests/io_/test_resolve_url.py
tests/io_/v0_0_0/__init__.py
tests/io_/v0_0_0/collection_l1.json
tests/io_/v0_0_0/collection_l2.json
tests/io_/v0_0_0/test_caching_backend.py
tests/io_/v0_0_0/test_disk_backend.py
tests/io_/v0_0_0/test_http_backend.py
tests/io_/v0_0_0/test_missing_shape.py
tests/io_/v0_0_0/test_reader.py
tests/io_/v0_0_0/test_write.py
tests/io_/v0_0_0/tileset.json
tests/utils/__init__.py
tests/utils/contextchild.py