Metadata-Version: 1.0
Name: slicedimage
Version: 4.1.0
Summary: Library to access sliced imaging data
Home-page: UNKNOWN
Author: Tony Tung
Author-email: ttung@chanzuckerberg.com
License: MIT
Platform: UNKNOWN
